pppy/__init__.py
pppy/pppy.py
pppy/pppyComp.py
pppy-1.1.0.dist-info/licenses/LICENCE-fr.txt
pppy-1.1.0.dist-info/licenses/LICENSE-en.txt
pppy-1.1.0.dist-info/METADATA
pppy-1.1.0.dist-info/WHEEL
pppy-1.1.0.dist-info/top_level.txt
pppy-1.1.0.dist-info/RECORD
